sgsim/__init__.py
sgsim/core/__init__.py
sgsim/core/domain.py
sgsim/core/engine.py
sgsim/core/functions.py
sgsim/core/model.py
sgsim/io/__init__.py
sgsim/io/reading_tools.py
sgsim/io/record_reader.py
sgsim/motion/__init__.py
sgsim/motion/ground_motion.py
sgsim/motion/signal.py
sgsim/optimization/__init__.py
sgsim/optimization/fit_eval.py
sgsim/optimization/fitting.py
sgsim-1.3.2.dist-info/licenses/LICENSE
sgsim-1.3.2.dist-info/METADATA
sgsim-1.3.2.dist-info/WHEEL
sgsim-1.3.2.dist-info/top_level.txt
sgsim-1.3.2.dist-info/RECORD
