Metadata-Version: 2.4
Name: sgsim
Version: 1.3.2
Summary: Python Package for Simulation and Analysis of Ground Motions
Author-email: Sajad Hussaini <hussaini.smsajad@gmail.com>
License-Expression: MIT
Project-URL: Homepage, https://github.com/Sajad-Hussaini/sgsim
Project-URL: Repository, https://github.com/Sajad-Hussaini/sgsim
Project-URL: Issues, https://github.com/Sajad-Hussaini/sgsim/issues
Keywords: sgsim,stochastic ground motion simulation,ground motion analysis,earthquake engineering
Classifier: Programming Language :: Python :: 3
Classifier: Operating System :: OS Independent
Classifier: Intended Audience :: Science/Research
Classifier: Topic :: Scientific/Engineering
Requires-Python: >=3.10
License-File: LICENSE
Requires-Dist: numpy
Requires-Dist: scipy
Requires-Dist: numba
Provides-Extra: docs
Requires-Dist: sphinx; extra == "docs"
Requires-Dist: sphinx_rtd_theme; extra == "docs"
Requires-Dist: sphinx-copybutton; extra == "docs"
Requires-Dist: myst-parser; extra == "docs"
Requires-Dist: nbsphinx; extra == "docs"
Requires-Dist: pygments; extra == "docs"
Requires-Dist: pydata-sphinx-theme; extra == "docs"
Dynamic: license-file
